{"_id":"5894aba4d6e082157ed8783b","multithingId":"5894ab6f4770716d138a2d68","itemProps":[{"id":"5893889d0450e95f13425bc9"},{"id":"589388b3ab445577136b4f4d"},{"id":"588cae06d25fe46a134af74e"},{"id":"5895e3ff8a8228e30f2458d3"},{"id":"5894b0b2630ae26e130a74c9"},{"id":"58963b342f5bbd84136d4854"},{"id":"5895e38ce22f49dc0f8eeb7b"},{"id":"5895da4f783992761372f2da"},{"id":"58bad24e0bacb5f60f42a09f"},{"id":"5893889d0450e95f13425bc9","rot":"2"},{"id":"58963a949cd2eeda0f301da6","state":"1"}],"staticItemsPropIndexAndXY":[["0","84","1"],["0","239","1"],["1","84","18"],["1","239","20"],["1","84","37"],["1","239","37"],["1","84","56"],["1","239","56"],["1","84","75"],["2","104","75"],["2","215","75"],["1","239","75"],["3","29","93"],["3","294","93"],["1","84","94"],["1","239","94"],["4","160","103"],["1","84","113"],["1","239","113"],["5","160","125"],["1","84","132"],["6","104","132"],["6","215","132"],["1","239","132"],["1","84","151"],["7","159","151"],["1","239","151"],["8","160","154"],["9","84","170"],["9","239","170"]],"movableItemsPropIndexAndXY":[["10","3","122"],["10","17","122"],["10","32","122"],["10","48","122"],["10","264","123"],["10","281","123"],["10","296","123"],["10","311","123"]],"settings":{"hasNeutralSections":"true","hasParticipantSections":"true","fontName":"black","maxParticipants":"2","movableItemsRevealMode":"fromCenterBelow"}}